copyjindu/__init__.py
copyjindu/core.py
copyjindu-1.0.2.dist-info/METADATA
copyjindu-1.0.2.dist-info/WHEEL
copyjindu-1.0.2.dist-info/top_level.txt
copyjindu-1.0.2.dist-info/RECORD
